ost_kit_python/__init__.py
ost_kit_python-0.0.4.dist-info/METADATA
ost_kit_python-0.0.4.dist-info/RECORD
ost_kit_python-0.0.4.dist-info/WHEEL
ost_kit_python-0.0.4.dist-info/top_level.txt
