Metadata-Version: 2.1
Name: ost-kit-python
Version: 0.0.4
Summary: OST Kit API wrapper for Python
Home-page: https://github.com/paste/ost-kit-python
Author: Aaron Oxborrow
License: UNKNOWN
Platform: UNKNOWN
Classifier: Development Status :: 3 - Alpha
Classifier: Programming Language :: Python :: 2
Classifier: Programming Language :: Python :: 3
Classifier: License :: OSI Approved :: MIT License
Classifier: Operating System :: OS Independent
Requires-Dist: requests
Requires-Dist: urllib3
